setup.py
entroport/__init__.py
entroport/entroport.py
entroport/utils.py
entroport.egg-info/PKG-INFO
entroport.egg-info/SOURCES.txt
entroport.egg-info/dependency_links.txt
entroport.egg-info/not-zip-safe
entroport.egg-info/top_level.txt