Metadata-Version: 1.0
Name: entroport
Version: 0.1
Summary: portfolio allocation with relative entropy minimization
Home-page: http://github.com/nuffe/entroport
Author: nuffe
Author-email: UNKNOWN
License: MIT
Platform: UNKNOWN
